proms/__init__.py
proms/__main__.py
proms/config.py
proms/dataset.py
proms/fs_methods.py
proms/k_medoids.py
proms/predict.py
proms/utils.py
proms-1.0.12.dist-info/LICENSE
proms-1.0.12.dist-info/METADATA
proms-1.0.12.dist-info/WHEEL
proms-1.0.12.dist-info/entry_points.txt
proms-1.0.12.dist-info/top_level.txt
proms-1.0.12.dist-info/RECORD
