Metadata-Version: 2.1
Name: proms
Version: 1.0.12
Summary: Protein Markers Selection
Home-page: https://github.com/bzhanglab/proms
Download-URL: https://github.com/bzhanglab/proms/archive/1.0.12.tar.gz
Author: Zhiao Shi
Author-email: zhiao.shi@gmail.com
License: MIT
Keywords: machine learning,feature selection,proteomics,multiomics,biomarker,genomics,bioinformatics
Classifier: License :: OSI Approved :: MIT License
Classifier: Programming Language :: Python
Classifier: Programming Language :: Python :: 2
Classifier: Programming Language :: Python :: 3
Requires-Python: >=3.6
License-File: LICENSE
Requires-Dist: scikit-survival
Requires-Dist: numpy
Requires-Dist: scipy
Requires-Dist: scikit-learn
Requires-Dist: pandas
Requires-Dist: xgboost
Requires-Dist: matplotlib
Requires-Dist: pyyaml
